README.md
setup.py
netbox_scripts_lib/__init__.py
netbox_scripts_lib/email.py
netbox_scripts_lib.egg-info/PKG-INFO
netbox_scripts_lib.egg-info/SOURCES.txt
netbox_scripts_lib.egg-info/dependency_links.txt
netbox_scripts_lib.egg-info/requires.txt
netbox_scripts_lib.egg-info/top_level.txt