Metadata-Version: 2.1
Name: netbox-scripts-lib
Version: 0.2
Summary: Shared lib of functions and tools for NetBox Custom Scripts
Author: Jiri Vrany
Author-email: jiri.vrany@cesnet.cz
